ecocal/Calendar.py
ecocal/Event.py
ecocal/__init__.py
ecocal/constants.py
ecocal/utils.py
ecocal-1.2.0.dist-info/AUTHORS
ecocal-1.2.0.dist-info/LICENSE
ecocal-1.2.0.dist-info/METADATA
ecocal-1.2.0.dist-info/WHEEL
ecocal-1.2.0.dist-info/top_level.txt
ecocal-1.2.0.dist-info/RECORD
