Metadata-Version: 2.1
Name: ecocal
Version: 1.2.0
Summary: Worldwide economic calendar Python package (details, estimates, market news, ...)
Home-page: https://github.com/lcsrodriguez/ecocal
Author: Lucas RODRIGUEZ
Author-email: lcsrodriguez@pm.me
License: MIT
Classifier: Programming Language :: Python :: 3
Classifier: License :: OSI Approved :: MIT License
Classifier: Operating System :: OS Independent
Requires-Python: >=3.10
License-File: LICENSE
License-File: AUTHORS
Requires-Dist: requests (==2.31.0)
Requires-Dist: pandas (==2.1.4)
Requires-Dist: tqdm (==4.66.1)
Requires-Dist: notebook (==7.0.6)
